linux_tutorial_nabla-0.1.3.dist-info/METADATA
linux_tutorial_nabla-0.1.3.dist-info/WHEEL
linux_tutorial_nabla-0.1.3.dist-info/entry_points.txt
linux_tutorial_nabla/__init__.py
linux_tutorial_nabla/__main__.py
linux_tutorial_nabla/colors.py
linux_tutorial_nabla/common.py
linux_tutorial_nabla/tab_completer.py
linux_tutorial_nabla/terminal.py
linux_tutorial_nabla/tutorial.py
linux_tutorial_nabla/tutorial_handler.py
linux_tutorial_nabla/tutorials/__init__.py
linux_tutorial_nabla/tutorials/file_1.py
linux_tutorial_nabla/tutorials/navigation.py
linux_tutorial_nabla-0.1.3.dist-info/RECORD
