Metadata-Version: 2.1
Name: linux_tutorial_nabla
Version: 0.1.3
Summary: Interactive Linux tutorial for beginners
Author-Email: =?utf-8?q?Martin_Sundal_Asp=C3=A5s?= <martin.s.aspas@gmail.com>
License: MIT
Requires-Python: >=3.10
Requires-Dist: pydantic>=2.9.2
Requires-Dist: colorama>=0.4.6
